cleaner/__init__.py
cleaner/cli.py
cleaner/filesystem.py
cleaner/shell.py
cleaner-0.4.0.dist-info/DESCRIPTION.rst
cleaner-0.4.0.dist-info/METADATA
cleaner-0.4.0.dist-info/RECORD
cleaner-0.4.0.dist-info/WHEEL
cleaner-0.4.0.dist-info/entry_points.txt
cleaner-0.4.0.dist-info/metadata.json
cleaner-0.4.0.dist-info/top_level.txt
