Metadata-Version: 1.1
Name: cleaner
Version: 0.4.0
Summary: Cleaner is a cool interactive shell that allows you to clean your directories with less eforts.
Home-page: https://github.com/Shir0kamii/cleaner
Author: UNKNOWN
Author-email: shir0kamii@gmail.com
License: UNKNOWN
Download-URL: https://github.com/Shir0kamii/cleaner/tags
Platform: any
Classifier: Programming Language :: Python
Classifier: Programming Language :: Python :: 3.4
Classifier: Programming Language :: Python :: 3.5
